[{"id":"HAKE38RZQF","type":"solar","name":"SolarPowerCo_EnergyGenerator","location":"Srinagar","power_production":251,"power_rating":482,"efficiency":0.52,"status":"off"},{"id":"UOU73AOUCB","type":"wind","name":"WindEnergyCorp_Turbine","location":"Jammu","power_production":1200,"turbine_height":80,"status":"ok"},{"id":"OJMBXXHKVB","type":"solar","name":"SunEnergy_SolarCell","location":"Udhampur","power_production":461,"power_rating":674,"efficiency":0.68,"status":"ok"},{"id":"KDCNMGQD05","type":"solar","name":"SolarWorld_PowerStation","location":"Leh","power_production":347,"power_rating":550,"efficiency":0.63,"status":"ok"},{"id":"EYIHJYC41X","type":"hydro","name":"HydroPowerTech_Dam","location":"Anantnag","water_flow":1000,"power_production":500,"status":"ok"},{"id":"2SVOG8Y4RJ","type":"battery","name":"EnergyStorage_BatteryBank","location":"Baramulla","capacity":1000,"charge_level":64,"status":"ok"},{"id":"ONXSXW314T","type":"street_light","name":"CityLighting_MainStreet","location":"Doda","lamp_count":100,"power_usage":200,"status":"ok"}]